cvfem/__init__.py
cvfem-0.0.0.dist-info/LICENSE.txt
cvfem-0.0.0.dist-info/METADATA
cvfem-0.0.0.dist-info/WHEEL
cvfem-0.0.0.dist-info/top_level.txt
cvfem-0.0.0.dist-info/RECORD
